twitch_dota_layerth/api.py
twitch_dota_layerth/lib.py
twitch_dota_layerth/tooltips.py
twitch_dota_layerth-0.1.0.dist-info/METADATA
twitch_dota_layerth-0.1.0.dist-info/WHEEL
twitch_dota_layerth-0.1.0.dist-info/RECORD
